zllm_kit/__init__.py
zllm_kit/py.typed
zllm_kit-0.1.0.dist-info/METADATA
zllm_kit-0.1.0.dist-info/WHEEL
zllm_kit-0.1.0.dist-info/licenses/LICENSE
zllm_kit-0.1.0.dist-info/RECORD
