Metadata-Version: 2.4
Name: zllm-kit
Version: 0.1.0
Summary: LLM quantization framework
Author-email: Vladimir Malinovskii <galqiwi@gmail.com>
License-File: LICENSE
Requires-Python: >=3.10
